nonebot_plugin_session/__init__.py
nonebot_plugin_session/adapters/__init__.py
nonebot_plugin_session/adapters/console.py
nonebot_plugin_session/adapters/discord.py
nonebot_plugin_session/adapters/dodo.py
nonebot_plugin_session/adapters/feishu.py
nonebot_plugin_session/adapters/kaiheila.py
nonebot_plugin_session/adapters/onebot_v11.py
nonebot_plugin_session/adapters/onebot_v12.py
nonebot_plugin_session/adapters/qq.py
nonebot_plugin_session/adapters/red.py
nonebot_plugin_session/adapters/satori.py
nonebot_plugin_session/adapters/telegram.py
nonebot_plugin_session/const.py
nonebot_plugin_session/extractor.py
nonebot_plugin_session/session.py
nonebot_plugin_session-0.3.1.dist-info/LICENSE
nonebot_plugin_session-0.3.1.dist-info/METADATA
nonebot_plugin_session-0.3.1.dist-info/WHEEL
nonebot_plugin_session-0.3.1.dist-info/RECORD
