Metadata-Version: 2.1
Name: nonebot_plugin_session
Version: 0.3.1
Summary: Nonebot2 会话信息提取与会话id定义
Home-page: https://github.com/noneplugin/nonebot-plugin-session
License: MIT
Author: meetwq
Author-email: meetwq@gmail.com
Requires-Python: >=3.8,<4.0
Classifier: License :: OSI Approved :: MIT License
Classifier: Programming Language :: Python :: 3
Classifier: Programming Language :: Python :: 3.8
Classifier: Programming Language :: Python :: 3.9
Classifier: Programming Language :: Python :: 3.10
Classifier: Programming Language :: Python :: 3.11
Classifier: Programming Language :: Python :: 3.12
Requires-Dist: nonebot2 (>=2.0.0,<3.0.0)
Requires-Dist: strenum (>=0.4.8,<0.5.0)
Project-URL: Repository, https://github.com/noneplugin/nonebot-plugin-session
